entity_gym_rs-0.1.1.dist-info/METADATA
entity_gym_rs-0.1.1.dist-info/WHEEL
entity_gym_rs-0.1.1.dist-info/license_files/LICENSE-APACHE
entity_gym_rs-0.1.1.dist-info/license_files/LICENSE-MIT
entity_gym_rs/__init__.py
entity_gym_rs/entity_gym_rs.cpython-36m-x86_64-linux-gnu.so
entity_gym_rs-0.1.1.dist-info/RECORD
