Metadata-Version: 2.1
Name: entity-gym-rs
Version: 0.1.1
Requires-Dist: numpy~=1.22.3
Requires-Dist: ragged-buffer~=0.3.7
Requires-Dist: entity-gym~=0.1.5
License-File: LICENSE-APACHE
License-File: LICENSE-MIT
Summary: Rust bindings for the entity-gym library
Author: Clemens Winter <clemenswinter1@gmail.com>
Author-email: Clemens Winter <clemenswinter1@gmail.com>
License: MIT OR Apache-2.0
Requires-Python: >=3.6
Project-URL: Source Code, https://github.com/entity-neural-network/entity-gym-rs
